{"title":"控制范围","slug":"PMP/项目范围管理/监控过程组/控制范围/控制范围","date":"2021-12-04T14:31:46.000Z","updated":"2023-09-08T06:12:36.609Z","comments":true,"path":"api/articles/PMP/项目范围管理/监控过程组/控制范围/控制范围.json","excerpt":null,"covers":["https://ddabb.github.io/photos/pmpimages/数据流向图/5.6控制范围.png"],"content":"<p>控制范围是监督项目和产品的范围状态，管理范围基准变更的过程。</p>\n<p>本过程的主要作用是，在整个项目期间保持对范围基准的维护，且需要在整个项目期间开展。<br><img src=\"https://ddabb.github.io/photos/pmpimages/数据流向图/5.6控制范围.png\"><br>控制项目范围确保所有变更请求、推荐的纠正措施或预防措施都通过实施整体变更控制过程（见 4.6 节）进行处理。</p>\n<p>在变更实际发生时，也要采用控制范围过程来管理这些变更。</p>\n<p>控制范围过程应该与其他控制过程协调开展。</p>\n<p>未经控制的产品或项目范围的扩大（未对时间、成本和资源做相应调整）被称为范围蔓延。</p>\n<p>变更不可避免，因此在每个项目上，都必须强制实施某种形式的变更控制。</p>\n","more":"<p>控制范围是监督项目和产品的范围状态，管理范围基准变更的过程。</p>\n<p>本过程的主要作用是，在整个项目期间保持对范围基准的维护，且需要在整个项目期间开展。<br><img src=\"https://ddabb.github.io/photos/pmpimages/数据流向图/5.6控制范围.png\"><br>控制项目范围确保所有变更请求、推荐的纠正措施或预防措施都通过实施整体变更控制过程（见 4.6 节）进行处理。</p>\n<p>在变更实际发生时，也要采用控制范围过程来管理这些变更。</p>\n<p>控制范围过程应该与其他控制过程协调开展。</p>\n<p>未经控制的产品或项目范围的扩大（未对时间、成本和资源做相应调整）被称为范围蔓延。</p>\n<p>变更不可避免，因此在每个项目上，都必须强制实施某种形式的变更控制。</p>\n","categories":[{"name":"项目管理","path":"api/categories/项目管理.json"}],"tags":[{"name":"PMP","path":"api/tags/PMP.json"},{"name":"监控过程组","path":"api/tags/监控过程组.json"},{"name":"项目范围管理","path":"api/tags/项目范围管理.json"},{"name":"控制范围","path":"api/tags/控制范围.json"}]}